README.md
setup.py
atlas_client/__init__.py
atlas_client/atlas.py
atlas_client/exceptions.py
atlas_client/pipeline.py
atlas_explorer_client.egg-info/PKG-INFO
atlas_explorer_client.egg-info/SOURCES.txt
atlas_explorer_client.egg-info/dependency_links.txt
atlas_explorer_client.egg-info/requires.txt
atlas_explorer_client.egg-info/top_level.txt