Metadata-Version: 2.1
Name: atlas-explorer-client
Version: 0.0.3
Summary: A python client for interacting with the Atlas text explorer.
Home-page: https://github.com/nomic-ai/atlas_client
Author: nomic.ai
Author-email: support@nomic.ai
License: UNKNOWN
Platform: UNKNOWN
Classifier: License :: OSI Approved :: Apache Software License
Classifier: Programming Language :: Python :: 3
Provides-Extra: dev
